mkdocs_md_preview/__init__.py
mkdocs_md_preview/plugin.py
mkdocs_md_preview-1.0.0.dist-info/licenses/LICENSE
mkdocs_md_preview-1.0.0.dist-info/METADATA
mkdocs_md_preview-1.0.0.dist-info/WHEEL
mkdocs_md_preview-1.0.0.dist-info/entry_points.txt
mkdocs_md_preview-1.0.0.dist-info/top_level.txt
mkdocs_md_preview-1.0.0.dist-info/RECORD
