Metadata-Version: 2.4
Name: mkdocs-md-preview
Version: 1.0.0
Summary: MkDocs plugin for side-by-side markdown preview
Home-page: https://github.com/yourusername/mkdocs-md-preview
Author: Your Name
Author-email: Paul Liu <20290410+Paulkm2006@users.noreply.github.com>
License: MIT
Project-URL: Homepage, https://github.com/Paulkm2006/mkdocs-md-preview
Keywords: mkdocs,plugin,markdown,preview,side-by-side
Classifier: Development Status :: 4 - Beta
Classifier: Intended Audience :: Developers
Classifier: License :: OSI Approved :: MIT License
Classifier: Operating System :: OS Independent
Classifier: Programming Language :: Python :: 3
Classifier: Programming Language :: Python :: 3.7
Classifier: Programming Language :: Python :: 3.8
Classifier: Programming Language :: Python :: 3.9
Classifier: Programming Language :: Python :: 3.10
Classifier: Programming Language :: Python :: 3.11
Classifier: Topic :: Documentation
Classifier: Topic :: Software Development :: Documentation
Classifier: Topic :: Text Processing :: Markup :: Markdown
Requires-Python: >=3.7
License-File: LICENSE
Requires-Dist: mkdocs>=1.0
Requires-Dist: markdown>=3.0
Dynamic: author
Dynamic: home-page
Dynamic: license-file
Dynamic: requires-python
